{
  "last_updated": "2026-04-16T19:18:14.953517Z",
  "updated_by": "update_intelligence.py v3 (GitHub Actions)",
  "global_signal": "BUY",
  "global_summary": "Akkumulieren – günstige Phase aktiv",
  "fear_greed": 23,
  "btc_price_usd": 74830,
  "btc_ath_dist_pct": -31.3,
  "btc_30d_change_pct": 2.98,
  "next_update": "2026-04-23T18:00:00Z",
  "ai_weekly_briefing": {
    "title": "BTC-Kaufsignal bei moderater Angst",
    "status": "Portfolio stabil, alle Positionen im Plan, BTC zeigt Einstiegschance.",
    "insight": "Fear & Greed bei 23/100 signalisiert Marktangst – optimales Umfeld für planmäßiges DCA. Makro bleibt volatil (DXY 98.21, 10Y 4.31%), aber kein Grund zur Positionsänderung.",
    "action": "Monatliches DCA wie geplant ausführen, BTC-Anteil bevorzugt erhöhen, Metaplanet-NAV 1.14x beobachten."
  },
  "market_regime": "fearful",
  "btc_dominance_pct": 57.0,
  "macro": {
    "sp500": 7032.84,
    "dxy": 98.21,
    "gold": 4813.6,
    "us10y": 4.31,
    "usdjpy": 159.18
  },
  "next_halving": {
    "next_halving_estimated_utc": "2028-04-12T08:58:21Z",
    "next_halving_block": 1050000,
    "blocks_remaining": 104626,
    "current_block_height": 945374,
    "halving_source": "blockchain_calculated"
  }
}